{
	"slider": [
		{
			"id": 1,
			"title": "Vegetables big sale",
			"subTitle": "Fresh farm products",
			"text": "10% certifled-organic mix of fruit and veggies. Perfect for weekly cooking and snacking!",
			"img": "http://localhost:5000/assets/images/slider/1.jpg"
		},
		{
			"id": 2,
			"title": "Fresh vegetables",
			"subTitle": "Natural farm products",
			"text": "Widest range of farm-fresh Vegetables, Fruits & seasonal produce",
			"img": "http://localhost:5000/assets/images/slider/2.jpg"
		},
		{
			"id": 3,
			"title": "Fresh tomatoes",
			"subTitle": "Natural farm products",
			"text": "Natural organic tomatoes make your health stronger. Put your information here",
			"img": "http://localhost:5000/assets/images/slider/3.jpg"
		}
	],
	"offers": [
		{
            "id": 12,
            "img": "http://localhost:5000/assets/images/offerlinks/1.png"
        },
		{
            "id": 2,
            "img": "http://localhost:5000/assets/images/offerlinks/2.png"
        }
	],
	"posts": [
        {
            "id": 1,
			"title": "Funny Story",
			"date": "23/6/2021",
            "img": "http://localhost:5000/assets/images/posts/1.png",
			"tags": ["specials", "holiday"],
			"text": "Lorem ipsum dolor sit amet, consectetur adipisicing elit. Perspiciatis doloribus itaque nulla, ratione laboriosam quisquam dolorum expedita libero facere eius repellat qui suscipit illum a fuga odio velit. sint laboriosam explicabo asperiores eaque minus, magnam nesciunt." 
        },
		{
            "id": 2,
			"title": "About Fruits",
			"date": "24/6/2021",
            "img": "http://localhost:5000/assets/images/posts/2.png",
			"tags": ["specials"],
			"text": "Lorem ipsum dolor sit amet, consectetur adipisicing elit. Perspiciatis doloribus itaque nulla, ratione laboriosam quisquam dolorum expedita libero facere eius repellat qui suscipit illum a fuga odio velit. sint laboriosam explicabo asperiores eaque minus, magnam nesciunt." 
        },
		{
            "id": 3,
			"title": "Special!",
			"date": "25/6/2021",
            "img": "http://localhost:5000/assets/images/posts/3.png",
			"tags": ["halloween", "holiday"],
			"text": "Lorem ipsum dolor sit amet, consectetur adipisicing elit. Perspiciatis doloribus itaque nulla, ratione laboriosam quisquam dolorum expedita libero facere eius repellat qui suscipit illum a fuga odio velit. sint laboriosam explicabo asperiores eaque minus, magnam nesciunt." 
        },
		{
            "id": 4,
			"title": "Check Description",
			"date": "29/6/2021",
            "img": "http://localhost:5000/assets/images/posts/1.png",
			"tags": ["New Year", "holiday"],
			"text": "Lorem ipsum dolor sit amet, consectetur adipisicing elit. Perspiciatis doloribus itaque nulla, ratione laboriosam quisquam dolorum expedita libero facere eius repellat qui suscipit illum a fuga odio velit. sint laboriosam explicabo asperiores eaque minus, magnam nesciunt." 
        },
		{
            "id": 5,
			"title": "New Products",
			"date": "02/7/2021",
            "img": "http://localhost:5000/assets/images/posts/2.png",
			"tags": ["specials", "holiday"],
			"text": "Lorem ipsum dolor sit amet, consectetur adipisicing elit. Perspiciatis doloribus itaque nulla, ratione laboriosam quisquam dolorum expedita libero facere eius repellat qui suscipit illum a fuga odio velit. sint laboriosam explicabo asperiores eaque minus, magnam nesciunt." 
        },
		{
            "id": 6,
			"title": "Halloweeeeen!",
			"date": "04/7/2021",
            "img": "http://localhost:5000/assets/images/posts/3.png",
			"tags": ["Free"],
			"text": "Lorem ipsum dolor sit amet, consectetur adipisicing elit. Perspiciatis doloribus itaque nulla, ratione laboriosam quisquam dolorum expedita libero facere eius repellat qui suscipit illum a fuga odio velit. sint laboriosam explicabo asperiores eaque minus, magnam nesciunt." 
        }
	],
	"sale": [
		{
			"id": 1,
			"title": "Black Friday !",
			"saleInfo": "Sale 50% OFF",
			"description": "all vegetable products",
			"img": "http://localhost:5000/assets/images/sale/1.png"
		}
	],
	"products": [
		{
			"id": 1,
			"name": "Cucumber",
			"description": "trust me, ok? Lorem ipsum dolor sit amet, consectetur adipisicing elit.",
			"price": "23.32$",
			"newprice": "13.31$",
			"img": "http://localhost:5000/assets/images/products/1.jpg",
			"quantity": 23,
			"category": "Vegetables",
			"sale": true,
			"new": false
		},
		{
			"id": 2,
			"name": "Onion",
			"description": "Don't trust him! Lorem ipsum dolor sit amet, consectetur adipisicing elit.",
			"price": "666.66$",
			"newprice": "11.11$",
			"img": "http://localhost:5000/assets/images/products/2.jpg",
			"quantity": 78,
			"category": "Fruits",
			"sale": false,
			"new": true
		},
		{
			"id": 3,
			"name": "Carrot",
			"description": "Lie is everywhere! Lorem ipsum dolor sit amet, consectetur adipisicing elit.",
			"price": "23.32$",
			"newprice": "13.31$",
			"img": "http://localhost:5000/assets/images/products/1.jpg",
			"quantity": 7,
			"category": "Vegetables",
			"sale": true,
			"new": true
		},
		{
			"id": 4,
			"name": "Looser",
			"description": "Look at me! Lorem ipsum dolor sit amet, consectetur adipisicing elit.",
			"price": "14.88$",
			"newprice": "",
			"img": "http://localhost:5000/assets/images/products/1.jpg",
			"quantity": 777,
			"category": "Vegetables",
			"sale": false,
			"new": false
		},
		{
			"id": 5,
			"name": "Cucumber",
			"description": "trust me, ok? Lorem ipsum dolor sit amet, consectetur adipisicing elit.",
			"price": "23.32$",
			"newprice": "13.31$",
			"img": "http://localhost:5000/assets/images/products/1.jpg",
			"quantity": 23,
			"category": "Vegetables",
			"sale": true,
			"new": false
		},
		{
			"id": 6,
			"name": "Onion",
			"description": "Don't trust him! Lorem ipsum dolor sit amet, consectetur adipisicing elit.",
			"price": "666.66$",
			"newprice": "11.11$",
			"img": "http://localhost:5000/assets/images/products/2.jpg",
			"quantity": 78,
			"category": "Fruits",
			"sale": false,
			"new": true
		},
		{
			"id": 7,
			"name": "Carrot",
			"description": "Lie is everywhere! Lorem ipsum dolor sit amet, consectetur adipisicing elit.",
			"price": "23.32$",
			"newprice": "13.31$",
			"img": "http://localhost:5000/assets/images/products/1.jpg",
			"quantity": 7,
			"category": "Vegetables",
			"sale": true,
			"new": true
		},
		{
			"id": 8,
			"name": "Looser",
			"description": "Look at me! Lorem ipsum dolor sit amet, consectetur adipisicing elit.",
			"price": "14.88$",
			"newprice": "",
			"img": "http://localhost:5000/assets/images/products/1.jpg",
			"quantity": 777,
			"category": "Vegetables",
			"sale": false,
			"new": false
		},
		{
			"id": 9,
			"name": "Cucumber",
			"description": "trust me, ok? Lorem ipsum dolor sit amet, consectetur adipisicing elit.",
			"price": "23.32$",
			"newprice": "13.31$",
			"img": "http://localhost:5000/assets/images/products/1.jpg",
			"quantity": 23,
			"category": "Vegetables",
			"sale": true,
			"new": false
		},
		{
			"id": 10,
			"name": "Onion",
			"description": "Don't trust him! Lorem ipsum dolor sit amet, consectetur adipisicing elit.",
			"price": "666.66$",
			"newprice": "11.11$",
			"img": "http://localhost:5000/assets/images/products/2.jpg",
			"quantity": 78,
			"category": "Fruits",
			"sale": false,
			"new": true
		},
		{
			"id": 11,
			"name": "Carrot",
			"description": "Lie is everywhere! Lorem ipsum dolor sit amet, consectetur adipisicing elit.",
			"price": "23.32$",
			"newprice": "13.31$",
			"img": "http://localhost:5000/assets/images/products/1.jpg",
			"quantity": 7,
			"category": "Vegetables",
			"sale": true,
			"new": true
		},
		{
			"id": 12,
			"name": "Looser",
			"description": "Look at me! Lorem ipsum dolor sit amet, consectetur adipisicing elit.",
			"price": "14.88$",
			"newprice": "",
			"img": "http://localhost:5000/assets/images/products/1.jpg",
			"quantity": 777,
			"category": "Vegetables",
			"sale": false,
			"new": false
		},
		{
			"id": 13,
			"name": "Cucumber",
			"description": "trust me, ok? Lorem ipsum dolor sit amet, consectetur adipisicing elit.",
			"price": "23.32$",
			"newprice": "13.31$",
			"img": "http://localhost:5000/assets/images/products/1.jpg",
			"quantity": 23,
			"category": "Vegetables",
			"sale": true,
			"new": false
		},
		{
			"id": 14,
			"name": "Onion",
			"description": "Don't trust him! Lorem ipsum dolor sit amet, consectetur adipisicing elit.",
			"price": "666.66$",
			"newprice": "11.11$",
			"img": "http://localhost:5000/assets/images/products/2.jpg",
			"quantity": 78,
			"category": "Fruits",
			"sale": false,
			"new": true
		},
		{
			"id": 15,
			"name": "Carrot",
			"description": "Lie is everywhere! Lorem ipsum dolor sit amet, consectetur adipisicing elit.",
			"price": "23.32$",
			"newprice": "13.31$",
			"img": "http://localhost:5000/assets/images/products/1.jpg",
			"quantity": 7,
			"category": "Vegetables",
			"sale": true,
			"new": true
		},
		{
			"id": 16,
			"name": "Looser",
			"description": "Look at me! Lorem ipsum dolor sit amet, consectetur adipisicing elit.",
			"price": "14.88$",
			"newprice": "",
			"img": "http://localhost:5000/assets/images/products/1.jpg",
			"quantity": 777,
			"category": "Vegetables",
			"sale": false,
			"new": false
		},
		{
			"id": 17,
			"name": "Cucumber",
			"description": "trust me, ok? Lorem ipsum dolor sit amet, consectetur adipisicing elit.",
			"price": "23.32$",
			"newprice": "13.31$",
			"img": "http://localhost:5000/assets/images/products/1.jpg",
			"quantity": 23,
			"category": "Vegetables",
			"sale": true,
			"new": false
		},
		{
			"id": 18,
			"name": "Onion",
			"description": "Don't trust him! Lorem ipsum dolor sit amet, consectetur adipisicing elit.",
			"price": "666.66$",
			"newprice": "11.11$",
			"img": "http://localhost:5000/assets/images/products/2.jpg",
			"quantity": 78,
			"category": "Fruits",
			"sale": false,
			"new": true
		},
		{
			"id": 19,
			"name": "Carrot",
			"description": "Lie is everywhere! Lorem ipsum dolor sit amet, consectetur adipisicing elit.",
			"price": "23.32$",
			"newprice": "13.31$",
			"img": "http://localhost:5000/assets/images/products/1.jpg",
			"quantity": 7,
			"category": "Vegetables",
			"sale": true,
			"new": true
		},
		{
			"id": 20,
			"name": "Looser",
			"description": "Look at me! Lorem ipsum dolor sit amet, consectetur adipisicing elit.",
			"price": "14.88$",
			"newprice": "",
			"img": "http://localhost:5000/assets/images/products/1.jpg",
			"quantity": 777,
			"category": "Vegetables",
			"sale": false,
			"new": false
		}
	],
	"dealweek": [
		{
			"id": 1,
			"name": "Capusta",
			"price": "14.88$",
			"newprice": "10.49$",
			"img": "http://localhost:5000/assets/images/products/1.jpg",
			"category": "Vegetables",
			"time": 360000,
			"sale": true,
			"new": false
		}
	]
}
